[
  {
    "host": "140.174.189.3",
    "port": 8233,
    "reliability": 1.0,
    "lastSeen": "2025-12-05T16:46:15Z"
  },
  {
    "host": "74.50.74.102",
    "port": 8233,
    "reliability": 1.0,
    "lastSeen": "2025-12-05T16:46:15Z"
  },
  {
    "host": "135.181.94.12",
    "port": 8233,
    "reliability": 1.0,
    "lastSeen": "2025-12-05T16:46:15Z"
  },
  {
    "host": "205.209.104.118",
    "port": 8233,
    "reliability": 1.0,
    "lastSeen": "2025-12-05T16:46:15Z"
  },
  {
    "host": "185.205.246.161",
    "port": 8233,
    "reliability": 1.0,
    "lastSeen": "2025-12-05T16:46:15Z"
  },
  {
    "host": "37.187.76.79",
    "port": 8233,
    "reliability": 1.0,
    "lastSeen": "2025-12-05T16:46:15Z"
  }
]
